CHANGES.rst
MANIFEST.in
README.rst
setup.py
htmllaundry/__init__.py
htmllaundry/cleaners.py
htmllaundry/configure.zcml
htmllaundry/tests.py
htmllaundry/utils.py
htmllaundry/z3cform.py
htmllaundry.egg-info/PKG-INFO
htmllaundry.egg-info/SOURCES.txt
htmllaundry.egg-info/dependency_links.txt
htmllaundry.egg-info/not-zip-safe
htmllaundry.egg-info/requires.txt
htmllaundry.egg-info/top_level.txt