Metadata-Version: 2.1
Name: htmllaundry
Version: 2.2
Summary: Simple HTML cleanup utilities
Home-page: UNKNOWN
Author: Wichert Akkerman
Author-email: wichert@wiggy.net
License: BSD
Keywords: html clean
Platform: UNKNOWN
Classifier: Intended Audience :: Developers
Classifier: License :: OSI Approved :: BSD License
Classifier: Operating System :: OS Independent
Classifier: Programming Language :: Python :: 2
Classifier: Programming Language :: Python :: 2.4
Classifier: Programming Language :: Python :: 2.5
Classifier: Programming Language :: Python :: 2.6
Classifier: Programming Language :: Python :: 2.7
Classifier: Programming Language :: Python :: 3
Classifier: Programming Language :: Python :: 3.2
Classifier: Topic :: Software Development :: Libraries :: Python Modules
Classifier: Topic :: Text Processing :: Markup :: HTML
Provides-Extra: z3cform
